llm_pyexecutor/__init__.py
llm_pyexecutor/constants.py
llm_pyexecutor/local_executor.py
llm_pyexecutor/logger.py
llm_pyexecutor/cli/__init__.py
llm_pyexecutor/cli/extractor.py
llm_pyexecutor/code/__init__.py
llm_pyexecutor/code/dependecies.py
llm_pyexecutor/code/exceptions.py
llm_pyexecutor/code/executor.py
llm_pyexecutor/code/extractor.py
llm_pyexecutor/environment_manager/__init__.py
llm_pyexecutor/environment_manager/exceptions.py
llm_pyexecutor/environment_manager/virtual_environment.py
llm_code_executor-0.4.0.dist-info/LICENSE
llm_code_executor-0.4.0.dist-info/METADATA
llm_code_executor-0.4.0.dist-info/WHEEL
llm_code_executor-0.4.0.dist-info/top_level.txt
llm_code_executor-0.4.0.dist-info/RECORD
